setup.py
src/pycel/__init__.py
src/pycel/addin.py
src/pycel/excelcompiler.py
src/pycel/excellib.py
src/pycel/excelutil.py
src/pycel/excelwrapper.py
src/pycel/tokenizer.py
src/pycel/version.py
src/pycel_x.egg-info/PKG-INFO
src/pycel_x.egg-info/SOURCES.txt
src/pycel_x.egg-info/dependency_links.txt
src/pycel_x.egg-info/requires.txt
src/pycel_x.egg-info/top_level.txt