Metadata-Version: 1.1
Name: pycel-x
Version: 3.0.0.1
Summary: A library for compiling excel spreadsheets to python code & visualizing them as a graph
Home-page: https://github.com/dgorissen/pycel
Author: Dirk Gorissen + CERN
Author-email: zern.exz@gmail.com
License: UNKNOWN
Platform: UNKNOWN
Classifier: Development Status :: 4 - Beta
Classifier: Intended Audience :: Developers
Classifier: Development Status :: 3 - Alpha
Classifier: Intended Audience :: Developers
Classifier: Topic :: Software Development :: Build Tools
Classifier: License :: OSI Approved :: MIT License
Classifier: Programming Language :: Python :: 3
Classifier: Programming Language :: Python :: 3.2
Classifier: Programming Language :: Python :: 3.3
Classifier: Programming Language :: Python :: 3.4
